setup.py
hse_search/__init__.py
hse_search/analyzers.py
hse_search/mapping.py
hse_search/query_parser.py
hse_search/query_result.py
hse_search/utils.py
hse_search.egg-info/PKG-INFO
hse_search.egg-info/SOURCES.txt
hse_search.egg-info/dependency_links.txt
hse_search.egg-info/not-zip-safe
hse_search.egg-info/requires.txt
hse_search.egg-info/top_level.txt
hse_search/index/__init__.py
hse_search/index/bigtable_index.py
hse_search/index/http_index.py
hse_search/index/index.py
hse_search/index/posterizer.py
hse_search/index/sharded_index.py
hse_search/index/worker_index_manager.py
hse_search/low_level/__init__.py
hse_search/low_level/wrapped.pyx
hse_search/query_components/__init__.py
hse_search/query_components/_and.py
hse_search/query_components/_filter.py
hse_search/query_components/_or.py
hse_search/query_components/bool.py
hse_search/query_components/boost.py
hse_search/query_components/field_boost.py
hse_search/query_components/interleave.py
hse_search/query_components/match.py
hse_search/query_components/must.py
hse_search/query_components/must_not.py
hse_search/query_components/query_component.py
hse_search/query_components/range.py
hse_search/query_components/scored_term.py
hse_search/query_components/should.py
hse_search/query_components/term.py
hse_search/query_components/terms.py