Metadata-Version: 1.0
Name: hse-search
Version: 0.0.17
Summary: !
Home-page: UNKNOWN
Author: Mark Hudson
Author-email: mark.cd.hudson@gmail.com
License: Apache 2.0
Platform: UNKNOWN
